strawpoll/__about__.py
strawpoll/__init__.py
strawpoll/api.py
strawpoll/errors.py
strawpoll/http.py
strawpoll/poll.py
strawpoll/utils.py
strawpoll.py-0.2.0.dist-info/DESCRIPTION.rst
strawpoll.py-0.2.0.dist-info/METADATA
strawpoll.py-0.2.0.dist-info/RECORD
strawpoll.py-0.2.0.dist-info/WHEEL
strawpoll.py-0.2.0.dist-info/metadata.json
strawpoll.py-0.2.0.dist-info/top_level.txt
