Metadata-Version: 2.0
Name: strawpoll.py
Version: 0.2.0
Summary: A python wrapper for the Strawpoll API.
Home-page: https://github.com/PapyrusThePlant/strawpoll.py
Author: PapyrusThePlant
Author-email: UNKNOWN
License: MIT
Keywords: strawpoll.py
Platform: UNKNOWN
Classifier: Development Status :: 5 - Production/Stable
Classifier: License :: OSI Approved :: MIT License
Classifier: Intended Audience :: Developers
Classifier: Natural Language :: English
Classifier: Operating System :: OS Independent
Classifier: Programming Language :: Python :: 3.4
Classifier: Programming Language :: Python :: 3.5
Classifier: Topic :: Software Development :: Libraries :: Python Modules
Classifier: Topic :: Utilities
Requires-Dist: aiohttp
Requires-Dist: requests
